[{"adult":false,"backdrop_path":"/5lTZyuBTNOfawsfPT8Q0cIg6qAF.jpg","genre_ids":[27,53],"id":1339713,"title":"オブセッション 災愛","original_language":"en","original_title":"Obsession","overview":"主人公は孤独で内向的な青年ベア（マイケル・ジョンストン）。想いを寄せる女性ニッキー（インディ・ナヴァレッティ）との距離を縮めたい一心で、“願いを叶える”という不気味なまじない「ワン・ウィッシュ・ウィロー」に手を出したことから、彼の日常は少しずつ狂い始める。純粋だったはずの恋愛感情は執着へと変貌し、“最愛”が“災愛”へと反転していく──。","popularity":595.2258,"poster_path":"/vJIRyV24YoZcF79EdmddbX6MlQP.jpg","release_date":"2026-07-17","softcore":false,"video":false,"vote_average":7.917,"vote_count":863,"media_type":"movie"},{"adult":false,"backdrop_path":"/ufSwlnECLoUbBjPrFqEQcWBzHwc.jpg","genre_ids":[10402,18],"id":936075,"title":"Michael／マイケル","original_language":"en","original_title":"Michael","overview":"圧倒的な歌唱力と革新的なダンスパフォーマンスで、アーティストの枠を超え、全世界的なアイコンとなった“キング・オブ・ポップ”＝マイケル・ジャクソン。彼は幼いころから兄弟と共に歌い続けていた。製鉄所で働く父・ジョセフは野心家で、「人生は勝つか負けるかだ」と言い放ち、息子たちに厳しいレッスンを課し、兄弟グループ“ジャクソン５”としてデビューさせた。彼らをみた聴衆は誰しもマイケルの圧倒的な歌声に酔いしれた。評判は広まり、ステージからステージへ人気は急上昇、モータウン・レコードと契約し、スターダムを駆け上がっていく。しかし、喝采の裏で彼はまだ一人の少年だった。孤独と重圧の中、唯一無条件の愛で支え続けたのが母・キャサリンだった。やがて青年となったマイケルに運命の出会いが訪れる。音楽史にその名を刻む名プロデューサー、クインシー・ジョーンズ。彼との出会いによってマイケルはグループの枠を超え、ソロアーティストとして前人未踏の音楽的創造性を爆発させていく。『オフ・ザ・ウォール』『スリラー』、歴史的メガヒットアルバムと名曲の数々を生み出し、全世界の寵児となっていくマイケル。しかし、その栄光の裏には、早熟の天才ゆえの孤独感、強権的な父親の呪縛、家族への愛と自分の中に溢れるビジョンとの間で葛藤する一人の人間の姿があった… そして今、音楽史を塗り替える存在——“キング・オブ・ポップ”伝説誕生の瞬間へ。","popularity":535.6645,"poster_path":"/A23qVaLfdpfQlJ9VS1vvP5m5UfS.jpg","release_date":"2026-06-12","softcore":false,"video":false,"vote_average":8.657,"vote_count":2704,"media_type":"movie"},{"adult":false,"backdrop_path":"/laR2dpcNpbv83jdlRUNAYPPjH90.jpg","genre_ids":[28,14,12],"id":931285,"title":"モータルコンバット／ネクストラウンド","original_language":"en","original_title":"Mortal Kombat II","overview":"","popularity":491.176,"poster_path":"/cizlMyB1XQMBOz5jwMQ1KVGnnTQ.jpg","release_date":"2026-06-05","softcore":false,"video":false,"vote_average":7.976,"vote_count":1486,"media_type":"movie"},{"adult":false,"backdrop_path":"/A2tzVTVtnTvpji96IZmleN78KKv.jpg","genre_ids":[27,35],"id":1239134,"title":"ブート・バングラ ～悪霊の館～","original_language":"hi","original_title":"भूत बंगला","overview":"宮殿を相続することになった男は、そこを妹の結婚式の会場にしようと思いつく。だが、実はその宮殿には呪われた過去があり、花嫁にまつわる恐ろしい迷信が言い伝えられていて...。","popularity":368.1664,"poster_path":"/79RBp8afL4u4z3nVGR78z6eIvBB.jpg","release_date":"2026-04-16","softcore":false,"video":false,"vote_average":5.56,"vote_count":25,"media_type":"movie"},{"adult":false,"backdrop_path":"/emK2hOB6ACiExT0lNLog9lAmMFL.jpg","genre_ids":[18,10749],"id":1226293,"title":"Salitan","original_language":"tl","original_title":"Salitan","overview":"","popularity":350.3415,"poster_path":"/rMgG7cWuq9O6zhhLs2CbqIKVA8V.jpg","release_date":"2024-02-16","softcore":false,"video":false,"vote_average":4.375,"vote_count":8,"media_type":"movie"}]