{"page":1,"results":[{"adult":false,"backdrop_path":"/h25oHn8FJHaImp8DneBhDJQHOpM.jpg","genre_ids":[99],"id":17073,"title":"スワップ・スワップ~伝説のセックスクラブ~","original_language":"en","original_title":"American Swing","overview":"1970年代後半、ニューヨークで公然とセックスを楽しめるナイトクラブをオープンさせた男の生き様と、スワッピング文化の栄華と衰退を描いたドキュメンタリー。製作・監督はTVドキュメンタリーなどを手掛けてきたマシュー・カウフマンと、ジャーナリストのジョン・ハート。1977年、不況や治安の悪化によりニューヨークはどん底状態にあった。しかし、市が財政崩壊の危機に直面している中、夜の世界を彩るナイトクラブは空前の盛り上がりを見せていた。ミッドタウンのディスコ“スタジオ54”には、コカインでハイになったセレブが集まり、ダウンタウンのライヴハウス“CBGB”には、社会に対する不満や怒りをぶちまけるパンクロッカーたちが、そして保守的なアッパー・ウエスト・サイドの芸術的建造物“アンソニア”の地下にあるナイトクラブ“プレイトーズ・リトリート（プラトンの隠れ家）”には、ごく普通のカップルたちが集い、ダンスフロアーで踊り、プールで泳ぎ、見知らぬ相手とのフリーセックスを楽しんでいた。オーナーであるラリー・レビンソン独自の発想から火がついた“プレイトーズ・リトリート”は、個人的な快楽を求める自己中心的な世代に支持され、公然とセックスを楽しめる場所として急速にその名が知れ渡っていく。階層に縛られることなくどんな人でも歓迎し、カップルたちはたったの35ドルで、この“裸の楽園”に足を踏み入れることができた。ラリーやそこに集う者たちにとって“プレイトーズ・リトリート”はユートピアだった。中には、「タイムマシーンのように忘却の彼方へ連れ去ってくれる場所だった」と言う者もいる。しかし1985年、恒例のニューイヤー・パーティ直前、市当局から閉鎖処分とされた“プレイトーズ・リトリート”は、その8年に及ぶ華やかな幕を閉じることになる……。","popularity":37.5865,"poster_path":"/d4rfQ9lEq0G1yNUOjHEofXlfk0Z.jpg","release_date":"2009-10-17","softcore":false,"video":false,"vote_average":4.895,"vote_count":19,"media_type":"movie"},{"adult":false,"backdrop_path":"/2iqLoDsatVBwAvHTEzI71p3qBe9.jpg","genre_ids":[99,80],"id":1662317,"title":"クラッシュ: 暴走したのは愛か狂気か","original_language":"en","original_title":"The Crash","overview":"10代の少女が運転していた車が建物に衝突し、恋人とその友人が死亡した。悲惨な事故と思われていた一件が、殺人事件に様変わりしていく過程を追ったドキュメンタリー。","popularity":25.8788,"poster_path":"/veskdPx4YUTmkrFrTs6zRJ8VV4E.jpg","release_date":"2026-05-14","softcore":false,"video":false,"vote_average":6.949,"vote_count":137,"media_type":"movie"},{"adult":false,"backdrop_path":"/mj3RFamNUleZB94zMWgGnJkQCAH.jpg","genre_ids":[36,28,12,10752,99],"id":1308767,"title":"Young Washington","original_language":"en","original_title":"Young Washington","overview":"","popularity":28.7635,"poster_path":"/ntW9zzhDmbt3sXDyPXb7SHVuDdB.jpg","release_date":"2026-07-02","softcore":false,"video":false,"vote_average":6,"vote_count":4,"media_type":"movie"},{"adult":false,"backdrop_path":"/oGD1dZvojZssnd9Ua6RUalEEHQu.jpg","genre_ids":[99,80],"id":1699155,"title":"テイラー・パーカーの歪んだ母性","original_language":"en","original_title":"Maternal Instinct","overview":"警察が止めた一台の車。運転していた女性は出産したばかりだと言う。だが赤ん坊も、車内の血も、彼女のものではなく...。ゆがんだウソが次々と明らかになっていく犯罪ドキュメンタリー。","popularity":21.8059,"poster_path":"/4KdmT71AGzDMp5hJbAu9vysKQKT.jpg","release_date":"2026-06-11","softcore":false,"video":false,"vote_average":7.13,"vote_count":92,"media_type":"movie"},{"adult":false,"backdrop_path":"/om1hoP6W0j54esiYMi9meYZ90Vq.jpg","genre_ids":[28,35,99],"id":1612018,"title":"Jackass: Best and Last","original_language":"en","original_title":"Jackass: Best and Last","overview":"","popularity":21.1128,"poster_path":"/tfgccePxnswMqhmtxafliLlcCVR.jpg","release_date":"2026-06-25","softcore":false,"video":false,"vote_average":6.643,"vote_count":21,"media_type":"movie"},{"adult":false,"backdrop_path":"/62a8bMDftwD9aU0dkXr4eN6Q5q2.jpg","genre_ids":[99,10770],"id":1522126,"title":"1000 Men and Me: The Bonnie Blue Story","original_language":"en","original_title":"1000 Men and Me: The Bonnie Blue Story","overview":"","popularity":14.833,"poster_path":"/5dcgoyf8nt6Xt4VSR6Nrn6nwhuz.jpg","release_date":"2025-07-29","softcore":false,"video":false,"vote_average":5.2,"vote_count":22,"media_type":"movie"},{"adult":false,"backdrop_path":"/2X2jnuBmTa4q34Eutv50r9Uk1FK.jpg","genre_ids":[99],"id":159008,"title":"Inequality for All","original_language":"en","original_title":"Inequality for All","overview":"","popularity":8.437,"poster_path":"/yGWDqQlRzIcvna4YoEYw1cZ7rmn.jpg","release_date":"2013-01-19","softcore":false,"video":false,"vote_average":7.508,"vote_count":123,"media_type":"movie"},{"adult":false,"backdrop_path":"/j2PHw1Kw8KmpqINJ7AKGjpuoSvF.jpg","genre_ids":[18,99],"id":537971,"title":"Mia","original_language":"es","original_title":"Mia","overview":"","popularity":14.7597,"poster_path":"/nEmw1fZOQp2qFGdrak3ipCbe31G.jpg","release_date":"2017-12-17","softcore":false,"video":false,"vote_average":6.2,"vote_count":32,"media_type":"movie"},{"adult":false,"backdrop_path":"/dzqvWTl5Y1B9P5nEivZPP8Y0WpU.jpg","genre_ids":[99,10749,18],"id":939099,"title":"swingers ZwingerZ","original_language":"es","original_title":"swingers ZwingerZ","overview":"","popularity":14.4501,"poster_path":"/lemo5hfG4w7Sm9mKjiIGmJ3hkYB.jpg","release_date":"2022-03-20","softcore":false,"video":false,"vote_average":7.2,"vote_count":4,"media_type":"movie"},{"adult":false,"backdrop_path":null,"genre_ids":[99,10751,18],"id":1719266,"title":"hi, Papa","original_language":"en","original_title":"hi, Papa","overview":"","popularity":13.5809,"poster_path":"/aZ1vRGmvJfMpj7q0xM4y1ESEt9e.jpg","release_date":"2026-06-04","softcore":false,"video":false,"vote_average":10,"vote_count":1,"media_type":"movie"},{"adult":false,"backdrop_path":"/1rHfxW2OtNUDV6d3rpRnHRZYMhp.jpg","genre_ids":[99,10402],"id":1715920,"title":"Ojos","original_language":"en","original_title":"Ojos","overview":"","popularity":15.6345,"poster_path":"/6Mrz9qPyJRsiN1WP4uGmImGTxjk.jpg","release_date":"2026-06-26","softcore":false,"video":false,"vote_average":10,"vote_count":1,"media_type":"movie"},{"adult":false,"backdrop_path":null,"genre_ids":[99,10751,18],"id":1656677,"title":"Ordinary Heroes","original_language":"en","original_title":"Ordinary Heroes","overview":"","popularity":11.9501,"poster_path":null,"release_date":"2028-01-01","softcore":false,"video":false,"vote_average":0,"vote_count":0,"media_type":"movie"},{"adult":false,"backdrop_path":"/bHSiPPPrRJCvuRmXxXIawGGXIaF.jpg","genre_ids":[27,99],"id":1718652,"title":"Tobi Zertrennguru","original_language":"en","original_title":"Tobi Zertrennguru","overview":"","popularity":13.6964,"poster_path":"/qbuZbvv0mGejHYR719k0ZysEQ45.jpg","release_date":"2024-03-13","softcore":false,"video":false,"vote_average":10,"vote_count":1,"media_type":"movie"},{"adult":false,"backdrop_path":"/70uUnpfe7en9x011UjpZoub101l.jpg","genre_ids":[99,18],"id":1430,"title":"ボウリング・フォー・コロンバイン","original_language":"en","original_title":"Bowling for Columbine","overview":"アメリカのジャーナリスト、マイケル・ムーアによるドキュメンタリー。アメリカの銃社会を取り上げ、各界の著名人に突撃取材を敢行。そのパフォーマンス的取材力は本作をリアルなエンタテインメントにしている。","popularity":10.6895,"poster_path":"/1Tmz3jNpY1TtayoBSveIu92Hco5.jpg","release_date":"2002-10-09","softcore":false,"video":false,"vote_average":7.516,"vote_count":1698,"media_type":"movie"},{"adult":false,"backdrop_path":"/5v8xp9eYmpvFOJSAudUz5Jq2ZYm.jpg","genre_ids":[99,18],"id":1584262,"title":"Geridə Qalanlar","original_language":"en","original_title":"Geridə Qalanlar","overview":"","popularity":15.9178,"poster_path":"/55i5AVg1d6jl59TrxqBP8UPZP7j.jpg","release_date":"2025-11-08","softcore":false,"video":false,"vote_average":10,"vote_count":1,"media_type":"movie"},{"adult":false,"backdrop_path":"/52t7nT1f117FW6gdG32DrQKxpU1.jpg","genre_ids":[99,10402],"id":1642859,"title":"Iron Maiden: Burning Ambition","original_language":"en","original_title":"Iron Maiden: Burning Ambition","overview":"","popularity":12.3533,"poster_path":"/yZqhFJDenLfgF1VygOOCNmAdS1P.jpg","release_date":"2026-05-07","softcore":false,"video":false,"vote_average":8.2,"vote_count":30,"media_type":"movie"},{"adult":false,"backdrop_path":"/4bpoWqTeI7hNr7c31FMLsq1VK9D.jpg","genre_ids":[99],"id":1665254,"title":"Life Asks","original_language":"en","original_title":"Life Asks","overview":"","popularity":14.1831,"poster_path":"/tu2DvQF8YMvC5eVZ1Ct5stOJaXk.jpg","release_date":"2026-01-30","softcore":false,"video":false,"vote_average":7,"vote_count":1,"media_type":"movie"},{"adult":false,"backdrop_path":"/9AJ3GcCsUhoVn3czRU4yxVkSsDE.jpg","genre_ids":[99],"id":1202285,"title":"Porn","original_language":"fr","original_title":"Porn","overview":"","popularity":9.0049,"poster_path":"/rbzySQcXmTvWOaaJAsFDlCjW8eG.jpg","release_date":"2023-05-16","softcore":false,"video":false,"vote_average":7.4,"vote_count":7,"media_type":"movie"},{"adult":false,"backdrop_path":"/fQQ5QzE8AAAvWJqPK09ZXPuu5lP.jpg","genre_ids":[99],"id":1492188,"title":"Las Cenizas","original_language":"es","original_title":"Las Cenizas","overview":"","popularity":14.5286,"poster_path":"/2P4E6pEit6zggadAi8s7Z3proXu.jpg","release_date":"2023-03-06","softcore":false,"video":false,"vote_average":10,"vote_count":2,"media_type":"movie"},{"adult":false,"backdrop_path":null,"genre_ids":[99],"id":1668174,"title":"Velvet Gods","original_language":"en","original_title":"Velvet Gods","overview":"","popularity":12.6787,"poster_path":"/aAfZghW6fVugIrtPPtoQbixbGGL.jpg","release_date":"2026-04-11","softcore":false,"video":false,"vote_average":6,"vote_count":1,"media_type":"movie"}],"total_pages":11188,"total_results":223750}