{"page":1,"results":[{"adult":false,"backdrop_path":null,"genre_ids":[99],"id":1495435,"original_language":"it","original_title":"Ultimo film","overview":"","popularity":25.0066,"poster_path":null,"release_date":"2023-10-09","title":"Ultimo film","video":false,"vote_average":0,"vote_count":0,"media_type":"movie"},{"adult":false,"backdrop_path":"/85BqDpCZSA5lzsRbANkchg0RFIf.jpg","genre_ids":[99],"id":1413097,"original_language":"en","original_title":"Melania","overview":"","popularity":31.8817,"poster_path":"/ba6Silct0Y4pyvrSv0Tj0Urmx9f.jpg","release_date":"2026-01-30","title":"Melania","video":false,"vote_average":2.767,"vote_count":15,"media_type":"movie"},{"adult":false,"backdrop_path":"/3CCKbVUFunqZ6DCLjaUJLsWpgU.jpg","genre_ids":[99],"id":392269,"original_language":"en","original_title":"The Divide","overview":"","popularity":19.5085,"poster_path":"/kkp8dRftSHIiNceNMrEzTfmr7IT.jpg","release_date":"2015-11-20","title":"The Divide","video":false,"vote_average":6.7,"vote_count":12,"media_type":"movie"},{"adult":false,"backdrop_path":"/xJiF1zt3fBV14bzf1MNuzrZ4tTp.jpg","genre_ids":[99],"id":413796,"original_language":"en","original_title":"EXPRMNTL","overview":"","popularity":15.1158,"poster_path":"/fKEmZzYnRdq19VhI93BKrL4Ixaw.jpg","release_date":"2016-10-08","title":"EXPRMNTL","video":false,"vote_average":0,"vote_count":0,"media_type":"movie"},{"adult":false,"backdrop_path":null,"genre_ids":[99,35],"id":1190459,"original_language":"en","original_title":"Early British Films from the Filmoteca de Catalunya 1897-1909","overview":"","popularity":12.8138,"poster_path":"/1KsGGa1QjllU26IVIrbYFpbjLSf.jpg","release_date":"2023-07-07","title":"Early British Films from the Filmoteca de Catalunya 1897-1909","video":false,"vote_average":0,"vote_count":0,"media_type":"movie"},{"adult":false,"backdrop_path":"/z2uuQasY4gQJ8VDAFki746JWeQJ.jpg","genre_ids":[99,12],"id":515042,"original_language":"en","original_title":"Free Solo","overview":"垂直に切り立った数百メートルもの岩壁を、命綱や安全装置なしで登るというクライミング・スタイル“フリーソロ”のドキュメンタリー。若きクライマーのオノルドに1年密着し、前人未到の世界を克明に記録していく。","popularity":17.0546,"poster_path":"/v4QfYZMACODlWul9doN9RxE99ag.jpg","release_date":"2018-09-28","title":"フリーソロ","video":false,"vote_average":7.911,"vote_count":1453,"media_type":"movie"},{"adult":false,"backdrop_path":"/vgLSR0QX39nLEbqgGlqVDIRx2JF.jpg","genre_ids":[99],"id":1538718,"original_language":"en","original_title":"Disneyland Handcrafted","overview":"","popularity":13.8548,"poster_path":"/81szv19zvs5fGqXtWau6tXzfC4T.jpg","release_date":"2026-01-22","title":"Disneyland Handcrafted","video":false,"vote_average":9.167,"vote_count":6,"media_type":"movie"},{"adult":false,"backdrop_path":"/n2WschLfgBrF2Dj0SkdCL94q2jC.jpg","genre_ids":[99,80],"id":1595481,"original_language":"en","original_title":"Kidnapped: Elizabeth Smart","overview":"14歳のときにユタ州の自宅から誘拐されるという恐ろしい経験をしたエリザベス・スマート。エリザベス本人の言葉と初公開の資料を交えて、事件の真相に迫るドキュメンタリー。","popularity":10.6657,"poster_path":"/hMVhZxgbFLXZcDUIZ10NGb6s8w4.jpg","release_date":"2026-01-20","title":"キッドナップ: エリザベス・スマート誘拐事件","video":false,"vote_average":7.1,"vote_count":31,"media_type":"movie"},{"adult":false,"backdrop_path":"/jycEYzpASmk6dUZGGt0lPSnyKSU.jpg","genre_ids":[99,80,18],"id":1031143,"original_language":"en","original_title":"Another Body","overview":"","popularity":9.3936,"poster_path":"/wilheE5NIfBRqNcDydoSo2t4OH5.jpg","release_date":"2023-10-20","title":"Another Body","video":false,"vote_average":6.7,"vote_count":11,"media_type":"movie"},{"adult":false,"backdrop_path":"/rgn18vzInpmqloFtcXVxUNfHdhv.jpg","genre_ids":[99],"id":158997,"original_language":"en","original_title":"American Promise","overview":"","popularity":9.4683,"poster_path":"/fhQsWqriTq1TjY8slKwaLYjl2Bn.jpg","release_date":"2013-10-18","title":"American Promise","video":false,"vote_average":6.7,"vote_count":6,"media_type":"movie"},{"adult":false,"backdrop_path":null,"genre_ids":[99],"id":1223261,"original_language":"en","original_title":"Sweet Dreams","overview":"","popularity":9.2639,"poster_path":null,"release_date":"2006-12-01","title":"Sweet Dreams","video":false,"vote_average":0,"vote_count":0,"media_type":"movie"},{"adult":false,"backdrop_path":"/vTcJyuk0uJLKEPCrjJTB2zzY7Np.jpg","genre_ids":[18,99],"id":537971,"original_language":"es","original_title":"Mia","overview":"","popularity":8.8238,"poster_path":"/nEmw1fZOQp2qFGdrak3ipCbe31G.jpg","release_date":"2017-12-17","title":"Mia","video":false,"vote_average":6.1,"vote_count":30,"media_type":"movie"},{"adult":false,"backdrop_path":"/edGuDPKY6qHBg9hYvmnvLjcFoy4.jpg","genre_ids":[99],"id":1610413,"original_language":"en","original_title":"One Last Adventure: The Making of Stranger Things 5","overview":"ダファー兄弟が一時代を築いたシリーズがついに完結。何年にもわたる惜しみない努力とプロフェッショナルの技で最終章を形にしていくまでの内幕を追ったドキュメンタリー。","popularity":8.214,"poster_path":"/aZhrAx5CevLfjXcGIG3wBXxDiAL.jpg","release_date":"2026-01-11","title":"ストレンジャー・シングス 未知の世界 5 ～\"最後の冒険\"の舞台裏～","video":false,"vote_average":7.61,"vote_count":59,"media_type":"movie"},{"adult":false,"backdrop_path":null,"genre_ids":[99],"id":390275,"original_language":"pt","original_title":"1968","overview":"","popularity":8.9258,"poster_path":"/jKN19qCZ43Zn6iAHF2JhiYUXNwt.jpg","release_date":"1968-03-29","title":"1968","video":false,"vote_average":0,"vote_count":0,"media_type":"movie"},{"adult":false,"backdrop_path":"/zecxlBpLx0aLIjNjX1IOZuaSgo0.jpg","genre_ids":[99],"id":1412113,"original_language":"ko","original_title":"오징어 게임: 시즌2 제작 이야기","overview":"歴代最高の大ヒットを記録したシリーズのシーズン2はいかにして作られたか。セットデザインからキャラクターアークまで、キャストと監督の独占インタビューを通して制作の舞台裏に迫る。","popularity":9.2476,"poster_path":"/yQGaui0bQ5Ai3KIFBB45nTeIqad.jpg","release_date":"2025-01-02","title":"イカゲーム: シーズン2の舞台裏","video":false,"vote_average":8.414,"vote_count":438,"media_type":"movie"},{"adult":false,"backdrop_path":"/iFZCmi2tqmpOPtkTIqmAIjuHSoT.jpg","genre_ids":[99,10402],"id":728103,"original_language":"it","original_title":"Sportin' Life","overview":"","popularity":8.3239,"poster_path":"/lhGoEMEAKmlVtjS0GlB4hf4WocG.jpg","release_date":"2020-09-06","title":"Sportin' Life","video":false,"vote_average":4.2,"vote_count":4,"media_type":"movie"},{"adult":false,"backdrop_path":null,"genre_ids":[99],"id":245744,"original_language":"en","original_title":"Hit & Run","overview":"","popularity":5.7531,"poster_path":"/e5L0yoevcl1UIZw0RBLxyyouhdx.jpg","release_date":"2000-08-04","title":"Hit & Run","video":false,"vote_average":7,"vote_count":1,"media_type":"movie"},{"adult":false,"backdrop_path":"/rSqNzmKzc4mbKbmpLNh1TpKPZKa.jpg","genre_ids":[99],"id":982089,"original_language":"en","original_title":"Elizabeth: The Unseen Queen","overview":"","popularity":7.7295,"poster_path":"/tux8o7Y1MV48S3kniLevj1xEpun.jpg","release_date":"2022-05-29","title":"Elizabeth: The Unseen Queen","video":false,"vote_average":6.375,"vote_count":8,"media_type":"movie"},{"adult":false,"backdrop_path":"/2a3CC6VpCjqZ23Fe18GstMGg5Pj.jpg","genre_ids":[99,53,80],"id":1400782,"original_language":"en","original_title":"The Perfect Neighbor","overview":"長きにわたる近隣トラブルがやがて命を奪う暴力事件へと発展してしまう。その様子を警察のボディカメラ映像で追跡しながら、恐怖や偏見、正当防衛法を掘り下げていくドキュメンタリー作品。","popularity":7.3251,"poster_path":"/2NE7yN45zo19o4LJr6JFxDWmh2b.jpg","release_date":"2025-10-10","title":"パーフェクト・ネイバー: 正当防衛法はどこへ向かうのか","video":false,"vote_average":6.785,"vote_count":172,"media_type":"movie"},{"adult":false,"backdrop_path":"/6lxVJ7FtF4aUTxWF8xKewImeZFy.jpg","genre_ids":[99],"id":1421292,"original_language":"es","original_title":"El gran Coco Legrand","overview":"","popularity":6.3323,"poster_path":"/h77Yjx0AyhYOpNZEvo4As34YgHj.jpg","release_date":"2025-03-27","title":"El gran Coco Legrand","video":false,"vote_average":0,"vote_count":0,"media_type":"movie"}],"total_pages":10467,"total_results":209324}