{"page":1,"results":[{"adult":false,"backdrop_path":"/tNONILTe9OJz574KZWaLze4v6RC.jpg","genre_ids":[9648,53],"id":1368166,"original_language":"en","original_title":"The Housemaid","overview":"","popularity":298.0136,"poster_path":"/mJGFduBPAzTKzOeCeTjBBOxnalB.jpg","release_date":"2025-12-18","title":"The Housemaid","video":false,"vote_average":7.196,"vote_count":1034,"media_type":"movie"},{"adult":false,"backdrop_path":"/cz4vLJrmaV1zJlRYbxqtvLzeLWB.jpg","genre_ids":[28,35,80,9648],"id":1168190,"original_language":"en","original_title":"The Wrecking Crew","overview":"疎遠になっていた異母兄弟のジョニーと、ジェームズが、不可解な父の死をきっかけに再会する。ハワイで真実を探る中で、埋もれていた秘密が明らかになり、家族を引き裂きかねない陰謀が浮上する。","popularity":262.7138,"poster_path":"/7YFpaq50aFt0v4IvDQikn8xpJqt.jpg","release_date":"2026-01-28","title":"レッキング・クルー","video":false,"vote_average":6.8,"vote_count":535,"media_type":"movie"},{"adult":false,"backdrop_path":"/5h2EsPKNDdB3MAtOk9MB9Ycg9Rz.jpg","genre_ids":[16,35,12,10751,9648],"id":1084242,"original_language":"en","original_title":"Zootopia 2","overview":"警察学校を無事卒業し警察官となったニックと、ウサギ初の警官として以前にもまして熱心に任務に挑むジュディが再びバディを組むことに！ある日、ズートピアに突如現れたヘビ・ゲイリーをきっかけに、ジュディとニックはズートピアの過去の歴史にまつわる巨大な謎に挑むことになる。そこでジュディとニックふたりの絆もこれまで以上に試されることになるのだが…。","popularity":216.4433,"poster_path":"/twxXtxn3bLoLQONWCRlCTrgDLpG.jpg","release_date":"2025-11-26","title":"ズートピア2","video":false,"vote_average":7.6,"vote_count":1637,"media_type":"movie"},{"adult":false,"backdrop_path":"/gLXibzLQ4qegvjdqDC0f8yTij2P.jpg","genre_ids":[9648,53,28],"id":1310568,"original_language":"en","original_title":"Murder at the Embassy","overview":"","popularity":133.6653,"poster_path":"/3DBmBItPdy0A2ol59jgHhS54Lua.jpg","release_date":"2025-11-14","title":"Murder at the Embassy","video":false,"vote_average":5.7,"vote_count":32,"media_type":"movie"},{"adult":false,"backdrop_path":"/eTodr0PX3fIDM4VFKJakpPGMZbp.jpg","genre_ids":[27,9648,53],"id":1528660,"original_language":"en","original_title":"Holy Ghost","overview":"","popularity":71.7109,"poster_path":"/z1lwn6GWAjJ7CSn80ZcURb0Cj4G.jpg","release_date":"2025-08-11","title":"Holy Ghost","video":false,"vote_average":6.286,"vote_count":7,"media_type":"movie"},{"adult":false,"backdrop_path":"/cJEfGBcVQElkQwD6nop9AcZy8X.jpg","genre_ids":[80,53,27,9648],"id":1194388,"original_language":"et","original_title":"Vari","overview":"","popularity":62.3728,"poster_path":"/t6hPGT2hGxn4E5VMWjEiLjkGNzt.jpg","release_date":"2024-10-18","title":"Vari","video":false,"vote_average":0,"vote_count":0,"media_type":"movie"},{"adult":false,"backdrop_path":"/ufqytAlziHq5pljKByGJ8IKhtEZ.jpg","genre_ids":[53,80,9648],"id":425274,"original_language":"en","original_title":"Now You See Me: Now You Don't","overview":"","popularity":59.429,"poster_path":"/2I7azmnMWidswvGeK4bWrPs2M5c.jpg","release_date":"2025-11-12","title":"グランド・イリュージョン／ダイヤモンド・ミッション","video":false,"vote_average":6.546,"vote_count":1028,"media_type":"movie"},{"adult":false,"backdrop_path":"/eftVUg9R1lys3wT8kHJqMaK64m7.jpg","genre_ids":[27,53,9648],"id":1212742,"original_language":"en","original_title":"The Rule of Jenny Pen","overview":"","popularity":53.6597,"poster_path":"/5vqK1wbrgmUvqHn6yPt9b6qT9iL.jpg","release_date":"2025-03-07","title":"The Rule of Jenny Pen","video":false,"vote_average":6.036,"vote_count":125,"media_type":"movie"},{"adult":false,"backdrop_path":"/3cVrg7tzSf5AgEecYWDOSAzXAeX.jpg","genre_ids":[27,9648],"id":1408208,"original_language":"ja","original_title":"８番出口","overview":"どこにでもある地下通路に迷い込んでしまった男。 “ご案内”に従って通路を進みつつも、次々と襲いかかる“異変”。 この空間は現実なのか？　幻想なのか？　 果たして、男は無事に地下通路から脱出できるのか？","popularity":49.1235,"poster_path":"/b2lOJsOPwLNjdewjcXIVXqqx25b.jpg","release_date":"2025-08-28","title":"８番出口","video":false,"vote_average":6.315,"vote_count":168,"media_type":"movie"},{"adult":false,"backdrop_path":"/sVB8MrQr0x7sqAj3KVpAqpCbapT.jpg","genre_ids":[27,9648],"id":680493,"original_language":"en","original_title":"Return to Silent Hill","overview":"","popularity":45.091,"poster_path":"/fqAGFN2K2kDL0EHxvJaXzaMUkkt.jpg","release_date":"2026-01-21","title":"Return to Silent Hill","video":false,"vote_average":5.2,"vote_count":130,"media_type":"movie"},{"adult":false,"backdrop_path":"/gqGQ0zADV5FIcgMWtWX8FcGQjFp.jpg","genre_ids":[27,878,9648],"id":1116201,"original_language":"en","original_title":"Iron Lung","overview":"","popularity":36.8479,"poster_path":"/sIwakdbMGS1krtgendTWpxTY9Hw.jpg","release_date":"2026-01-30","title":"Iron Lung","video":false,"vote_average":7.4,"vote_count":83,"media_type":"movie"},{"adult":false,"backdrop_path":"/yWCZc2TcsCYbMMjvUIsczmQi2TX.jpg","genre_ids":[27,9648,80],"id":1159559,"original_language":"en","original_title":"Scream 7","overview":"","popularity":35.6372,"poster_path":"/jjyuk0edLiW8vOSnlfwWCCLpbh5.jpg","release_date":"2026-02-25","title":"Scream 7","video":false,"vote_average":0,"vote_count":0,"media_type":"movie"},{"adult":false,"backdrop_path":"/ykigHs1OIyqqV04zfFqIlSHp546.jpg","genre_ids":[53,27,28,9648,878],"id":1412598,"original_language":"en","original_title":"Killer Whale","overview":"","popularity":35.0206,"poster_path":"/xC6zdIoIHjhOIFmjNyGgtzhuhiF.jpg","release_date":"2026-01-16","title":"Killer Whale","video":false,"vote_average":5.9,"vote_count":53,"media_type":"movie"},{"adult":false,"backdrop_path":"/zhoMwQofjgVec5Sin05hWECJtVQ.jpg","genre_ids":[18,53,80,9648],"id":1456349,"original_language":"fr","original_title":"Un simple accident","overview":"","popularity":31.4027,"poster_path":"/rlpI8BqpCccQ9zx6UlQ72g8KJPb.jpg","release_date":"2025-09-27","title":"Un simple accident","video":false,"vote_average":7.2,"vote_count":341,"media_type":"movie"},{"adult":false,"backdrop_path":"/ncI1PlBcANixIkgQSnjsSRz4OyT.jpg","genre_ids":[28,53,9648],"id":1439112,"original_language":"en","original_title":"Muzzle: City of Wolves","overview":"","popularity":29.1963,"poster_path":"/8qTMRmC07XCGidnKQFLbRM3FoDU.jpg","release_date":"2025-11-13","title":"Muzzle: City of Wolves","video":false,"vote_average":6.76,"vote_count":104,"media_type":"movie"},{"adult":false,"backdrop_path":"/aC6wW62V6b0csr5iUnbOjYAqfhg.jpg","genre_ids":[18,53,9648],"id":345,"original_language":"en","original_title":"Eyes Wide Shut","overview":"ニューヨークの開業医ビルとアリスの倦怠期を迎えている夫妻は、ビルの患者で友人のジーグラー夫妻が開いたクリスマス・パーティーに招かれる。このパーティでビルはピアニストであり旧友のニックと再会し、アリスはビルと別れて個別にパーティーを楽しむことにしたが、ビルは女性たちに誘惑され、一方でアリスはハンガリー人の紳士に誘惑される。","popularity":24.662,"poster_path":"/xepMThSANgfvHSUlyZUTve9qaTI.jpg","release_date":"1999-07-16","title":"アイズ ワイド シャット","video":false,"vote_average":7.484,"vote_count":6829,"media_type":"movie"},{"adult":false,"backdrop_path":"/fepnF3W4VP3s8ui8nDtrlsFVYwO.jpg","genre_ids":[28,9648,18],"id":1247002,"original_language":"ko","original_title":"파과","overview":"","popularity":24.3137,"poster_path":"/A9yJjkI7GdqeFYMyUe4PebA2NIw.jpg","release_date":"2025-04-30","title":"파과","video":false,"vote_average":6.4,"vote_count":53,"media_type":"movie"},{"adult":false,"backdrop_path":"/9mKhhHBfIAWy9TNVHAXqMEFokes.jpg","genre_ids":[27,9648],"id":1078605,"original_language":"en","original_title":"Weapons","overview":"","popularity":22.8417,"poster_path":"/kubQnf9HuQjcJ1LXtZRfVUfZN8z.jpg","release_date":"2025-08-04","title":"WEAPONS／ウェポンズ","video":false,"vote_average":7.28,"vote_count":2895,"media_type":"movie"},{"adult":false,"backdrop_path":"/iwgl8zlrrfvfWp9k9Paj8lvFEvS.jpg","genre_ids":[80,9648,53],"id":807,"original_language":"en","original_title":"Se7en","overview":"定年退職間近の刑事サマセットと新人のミルズは、ある殺人現場に向かう。そこには肥満の大男の凄惨な死体があった。またほどなくして、今度はビジネスマンの死体が発見される。サマセットはそれぞれの現場に残されていた文字から、犯人がキリスト教における七つの大罪(傲慢・嫉妬・憤怒・怠惰・強欲・暴食・色欲)に因んだ殺人に及んでいると分析、残るは5件となった。事件を未然に防ごうと犯人の特定を急ぐ2人。やがて一人の男が容疑者に浮上、しかし接近するも取り逃がし、さらなる犠牲者を出してしまう。そんな中、大罪に沿った犯行が残り2件となったところで、犯人を名乗る男が自首して来るのだが…。","popularity":22.2891,"poster_path":"/2g97P45nSbzgiHxpNtrxXAw0Apa.jpg","release_date":"1995-09-22","title":"セブン","video":false,"vote_average":8.378,"vote_count":22593,"media_type":"movie"},{"adult":false,"backdrop_path":"/rvtdN5XkWAfGX6xDuPL6yYS2seK.jpg","genre_ids":[80,9648,53],"id":414906,"original_language":"en","original_title":"The Batman","overview":"犯罪と戦う2年目のバットマンは、リドラーと呼ばれる連続殺人犯に直面しながら、自分の家族につながるゴッサム・シティの腐敗を暴く。","popularity":22.0202,"poster_path":"/25VVdDDHlJQmjUNYGu4m8jtm6GO.jpg","release_date":"2022-03-01","title":"THE BATMAN－ザ・バットマン－","video":false,"vote_average":7.656,"vote_count":11602,"media_type":"movie"}],"total_pages":1257,"total_results":25134}