{"page":1,"results":[{"adult":false,"backdrop_path":"/2meX1nMdScFOoV4370rqHWKmXhY.jpg","genre_ids":[10759,9648,18],"id":93405,"origin_country":["KR"],"original_language":"ko","original_name":"오징어 게임","overview":"勝てば天国、負ければ...即死。賞金に目がくらみ、奇妙なゲームへの招待を受けた参加者たちを待っていたのは、昔ながらの遊びを取り入れた死のゲームだった。","popularity":2182.1003,"poster_path":"/uFWMh3Z7ysKqMgyIpOTFr9Abk4e.jpg","first_air_date":"2021-09-17","name":"イカゲーム","vote_average":7.868,"vote_count":16143,"media_type":"tv"},{"adult":false,"backdrop_path":"/fQsIJQxE1D0Y0NpWSKwo489y5px.jpg","genre_ids":[10764],"id":204082,"origin_country":["GB"],"original_language":"en","original_name":"Squid Game: The Challenge","overview":"「イカゲーム」に着想を得たリアリティゲーム番組。456万ドルという人生を変えるような賞金を狙う456人のプレーヤーたちが、あらゆるスキルを駆使して究極のバトルに挑む。","popularity":219.2723,"poster_path":"/ypGrbrnaxNBSiSELXrl1D8st18s.jpg","first_air_date":"2023-11-22","name":"イカゲーム: ザ・チャレンジ","vote_average":6.4,"vote_count":539,"media_type":"tv"},{"adult":false,"backdrop_path":"/vyhmiHVWUvmH6jrfvtPdcwYc2I8.jpg","genre_ids":[10751,10762,16,10759,10765],"id":78173,"origin_country":["US"],"original_language":"en","original_name":"Dragons: Race to the Edge","overview":"人々とドラゴンが共に暮らすバイキングの世界で、心やさしい少年ヒックと相棒のドラゴン・トゥースが個性豊かな仲間たちとともに島を飛び出し、壮大な冒険を繰り広げる。","popularity":207.2912,"poster_path":"/uFozp1yQHWNHmQnnuSibCegAfed.jpg","first_air_date":"2015-06-26","name":"ヒックとドラゴン: 新たな世界へ!","vote_average":8.35,"vote_count":412,"media_type":"tv"},{"adult":false,"backdrop_path":"/tNi2aJPdCKfielGYzIi3IKxStz9.jpg","genre_ids":[10762,35],"id":502,"origin_country":["US"],"original_language":"en","original_name":"Sesame Street","overview":"","popularity":186.7161,"poster_path":"/14k9BfZ2p4rQBMeJ5crKTfUZVwD.jpg","first_air_date":"1969-11-10","name":"セサミストリート","vote_average":7.115,"vote_count":262,"media_type":"tv"},{"adult":false,"backdrop_path":"/vm4uFMgn1t71VFvPLZdeUuzKD7M.jpg","genre_ids":[35,18],"id":1424,"origin_country":["US"],"original_language":"en","original_name":"Orange Is the New Black","overview":"過去に犯した罪がバレ、刑務所に収監されたニューヨークの裕福な家庭のお嬢様を待っていたのは、女囚人たちの個性がぶつかる友情と裏切りの人間ドラマ。","popularity":158.0261,"poster_path":"/ekaa7YjGPTkFLcPhwWXTnARuCEU.jpg","first_air_date":"2013-07-11","name":"オレンジ・イズ・ニュー・ブラック","vote_average":7.659,"vote_count":2629,"media_type":"tv"},{"adult":false,"backdrop_path":"/A7zBjRDFh1TXG3Buhi55mmS1qSr.jpg","genre_ids":[10759,16,10765,10762],"id":66558,"origin_country":["US"],"original_language":"en","original_name":"Voltron: Legendary Defender","overview":"","popularity":157.816,"poster_path":"/yWAGNuPuUWJT9gIQmGdZiTGJWzh.jpg","first_air_date":"2016-06-10","name":"ヴォルトロン","vote_average":7.204,"vote_count":130,"media_type":"tv"},{"adult":false,"backdrop_path":"/bVml4IQKIS5DfPqgDoaZoRLlxIY.jpg","genre_ids":[16,10751,10762,35,10759],"id":64783,"origin_country":["US"],"original_language":"en","original_name":"Dawn of the Croods","overview":"","popularity":136.4983,"poster_path":"/cyCAsMLGECvEAFDfKcxcWy7YTOW.jpg","first_air_date":"2015-12-24","name":"Dawn of the Croods","vote_average":7.396,"vote_count":96,"media_type":"tv"},{"adult":false,"backdrop_path":"/fWOagGfFtMm70U8BtWPlVRW6efu.jpg","genre_ids":[18,9648],"id":259669,"origin_country":["ES"],"original_language":"es","original_name":"Olympo","overview":"きっかけは、ハイパフォーマンス・センターで1人の水泳選手が倒れたこと。高みを目指すあまり、仲間のアスリートたちが命をも脅かすリスクを負っている実態をアマイアは調べはじめるが...。","popularity":133.1278,"poster_path":"/6BgcsLnjFiizUFSZchctgeZJRzY.jpg","first_air_date":"2025-06-20","name":"オリンポ","vote_average":7.714,"vote_count":63,"media_type":"tv"},{"adult":false,"backdrop_path":"/u23G9KZregWHs1use6ir1fX27gl.jpg","genre_ids":[35,18],"id":81356,"origin_country":["GB"],"original_language":"en","original_name":"Sex Education","overview":"セラピストの母を持つオーティスは、経験もないのに性的な知識だけは豊富な高校生。人付き合いが苦手な彼だが、問題児のメイヴに誘われ、2人で秘密のセックス相談クリニックを始めることに。","popularity":131.2461,"poster_path":"/kWMqoiadg8hPdms4WG8uulKv6ZB.jpg","first_air_date":"2019-01-11","name":"セックス・エデュケーション","vote_average":8.236,"vote_count":7514,"media_type":"tv"},{"adult":false,"backdrop_path":"/oyi9AeavhrKTbISf4tZ83S7xp29.jpg","genre_ids":[10751,16,10759,35,10765],"id":68267,"origin_country":["US"],"original_language":"en","original_name":"Trollhunters: Tales of Arcadia","overview":"","popularity":123.5224,"poster_path":"/9VZmMzINVdO3ZYGsKItU39pNO2l.jpg","first_air_date":"2016-12-23","name":"トロールハンターズ: アルカディア物語","vote_average":8.443,"vote_count":1099,"media_type":"tv"},{"adult":false,"backdrop_path":"/zoAxfThy7ntyCutBeNgdaKhRoSX.jpg","genre_ids":[18],"id":1425,"origin_country":["US"],"original_language":"en","original_name":"House of Cards","overview":"","popularity":122.3868,"poster_path":"/hKWxWjFwnMvkWQawbhvC0Y7ygQ8.jpg","first_air_date":"2013-02-01","name":"ハウス・オブ・カード 野望の階段","vote_average":8.009,"vote_count":2898,"media_type":"tv"},{"adult":false,"backdrop_path":"/BA1cBwYLMQFfReDaXQZ5KmPpFf.jpg","genre_ids":[16,35,10762],"id":125004,"origin_country":["US"],"original_language":"en","original_name":"Littlest Pet Shop: A World of Our Own","overview":"","popularity":121.0778,"poster_path":"/dhksSgkzyNyqlcaUFuGRcJZZqrV.jpg","first_air_date":"2018-04-14","name":"Littlest Pet Shop: A World of Our Own","vote_average":7.1,"vote_count":15,"media_type":"tv"},{"adult":false,"backdrop_path":"/56v2KjBlU4XaOv9rVYEQypROD7P.jpg","genre_ids":[18,10765,9648],"id":66732,"origin_country":["US"],"original_language":"en","original_name":"Stranger Things","overview":"姿を消した少年、人目を忍び行われる数々の実験、破壊的な超常現象、突然現れた少女。すべての不可解な謎をつなぐのは、小さな町に隠された恐ろしい秘密。","popularity":120.1067,"poster_path":"/DGWUKWfKr03DoEDKZSR1DhNqA.jpg","first_air_date":"2016-07-15","name":"ストレンジャー・シングス 未知の世界","vote_average":8.6,"vote_count":18454,"media_type":"tv"},{"adult":false,"backdrop_path":"/mAXOCbZzvmDa6PCh5dcIPOB51Qc.jpg","genre_ids":[80,10765],"id":63174,"origin_country":["US"],"original_language":"en","original_name":"Lucifer","overview":"地獄の王として退屈で不幸なルシファー・モーニングスターは、王位を放棄してロサンゼルスに引退し、ロサンゼルス市警の刑事クロエ・デッカーと協力して犯罪者を倒した. しかし、彼が冥界から離れれば離れるほど、最悪の人類が逃れることができる脅威は大きくなります。","popularity":118.1013,"poster_path":"/ekZobS8isE6mA53RAiGDG93hBxL.jpg","first_air_date":"2016-01-25","name":"ルシファー","vote_average":8.447,"vote_count":15033,"media_type":"tv"},{"adult":false,"backdrop_path":"/dg3OindVAGZBjlT3xYKqIAdukPL.jpg","genre_ids":[10765,18,9648],"id":42009,"origin_country":["GB"],"original_language":"en","original_name":"Black Mirror","overview":"人間の醜さと最新のテクノロジーなどをテーマに、ひねりを効かせた予想外のストーリーを描き出す、現実の枠をこえたオムニバスシリーズ。","popularity":114.5683,"poster_path":"/seN6rRfN0I6n8iDXjlSMk1QjNcq.jpg","first_air_date":"2011-12-04","name":"ブラック・ミラー","vote_average":8.284,"vote_count":5561,"media_type":"tv"},{"adult":false,"backdrop_path":"/nBrkOZyI75artyizuBFeya48KbO.jpg","genre_ids":[16,10765],"id":86831,"origin_country":["US"],"original_language":"en","original_name":"Love, Death & Robots","overview":"不気味な魔物、度肝を抜く展開、ダークな笑いなどデヴィッド・フィンチャーとティム・ミラーの世界観がさく裂。職場で視聴厳禁な大人のアニメを集めたアンソロジー。","popularity":112.976,"poster_path":"/asDqvkE66EegtKJJXIRhBJPxscr.jpg","first_air_date":"2019-03-15","name":"ラブ、デス&ロボット","vote_average":8.234,"vote_count":3604,"media_type":"tv"},{"adult":false,"backdrop_path":"/ifZYdmNuMWimFCUGGcYAs9bHNlv.jpg","genre_ids":[10759,18,10768],"id":63333,"origin_country":["GB"],"original_language":"en","original_name":"The Last Kingdom","overview":"","popularity":108.7422,"poster_path":"/8eJf0hxgIhE6QSxbtuNCekTddy1.jpg","first_air_date":"2015-10-10","name":"ラスト・キングダム","vote_average":8.252,"vote_count":1819,"media_type":"tv"},{"adult":false,"backdrop_path":"/dQOphbONxlpPsKo30araFr0CYMO.jpg","genre_ids":[10765,18,10759],"id":71912,"origin_country":["US"],"original_language":"en","original_name":"The Witcher","overview":"リヴィア出身で変異体(ミュータント)のゲラルトは、怪物退治を請け負う凄腕ハンター。陰謀と策略が渦巻く戦国の世で、運命に導かれるように戦い続ける。","popularity":99.5267,"poster_path":"/oijWWO6CFfubsSsovsxk8QZiEnO.jpg","first_air_date":"2019-12-20","name":"ウィッチャー","vote_average":8.024,"vote_count":6175,"media_type":"tv"},{"adult":false,"backdrop_path":"/eGPH1IwktalozwCmeLTp3aPbHGC.jpg","genre_ids":[10764],"id":4656,"origin_country":["US"],"original_language":"en","original_name":"Raw","overview":"","popularity":95.8413,"poster_path":"/pv5WNnLUo7mpT8k901Lo8UovrqI.jpg","first_air_date":"1993-01-11","name":"WWE・ロウ","vote_average":6.778,"vote_count":333,"media_type":"tv"},{"adult":false,"backdrop_path":"/uU6YW3N11qECNfz18LNGAGg3Uir.jpg","genre_ids":[80,9648,18],"id":76669,"origin_country":["ES"],"original_language":"es","original_name":"Élite","overview":"労働者階級の子供 3 人がスペインで最も高級な学校に入学するとき、裕福な学生と貧しい学生の衝突が悲劇につながります。","popularity":93.3472,"poster_path":"/c07WqB99Igco0rua794q9k9QJYm.jpg","first_air_date":"2018-10-05","name":"エリート","vote_average":8.025,"vote_count":9249,"media_type":"tv"}],"total_pages":124,"total_results":2461}