{"page":1,"results":[{"adult":false,"backdrop_path":"/7jEnft2CLNbILWAiBRIBrXNN7Qh.jpg","genre_ids":[10767,35],"id":498,"origin_country":["US"],"original_language":"en","original_name":"Late Show with David Letterman","overview":"","popularity":882.0649,"poster_path":"/fTBC5EpsgKmli9VQcJMtqQ08Qj4.jpg","first_air_date":"1993-08-30","name":"Late Show with David Letterman","vote_average":6.325,"vote_count":154,"media_type":"tv"},{"adult":false,"backdrop_path":"/gMMnf8VRg3Z98WaFmOLr9Jk8pIs.jpg","genre_ids":[35,10767],"id":63770,"origin_country":["US"],"original_language":"en","original_name":"The Late Show with Stephen Colbert","overview":"","popularity":883.4531,"poster_path":"/9jkThAGYj2yp8jsS6Nriy5mzKFT.jpg","first_air_date":"2015-09-08","name":"ザ・レイト・ショー・ウィズ・スティーヴン・コルベア","vote_average":6.355,"vote_count":310,"media_type":"tv"},{"adult":false,"backdrop_path":"/kA50bkSC6bw5ZkutYrN9sLD9CZ9.jpg","genre_ids":[10767,35],"id":22980,"origin_country":["US"],"original_language":"en","original_name":"Watch What Happens Live with Andy Cohen","overview":"","popularity":766.3574,"poster_path":"/onSD9UXfJwrMXWhq7UY7hGF2S1h.jpg","first_air_date":"2009-07-16","name":"Watch What Happens Live with Andy Cohen","vote_average":5.127,"vote_count":75,"media_type":"tv"},{"adult":false,"backdrop_path":"/qLMfcvdCcCGD2BNLH8b6ZCBuO7D.jpg","genre_ids":[10763,35],"id":2224,"origin_country":["US"],"original_language":"en","original_name":"The Daily Show","overview":"","popularity":679.0343,"poster_path":"/ixcfyK7it6FjRM36Te4OdblAq4X.jpg","first_air_date":"1996-07-22","name":"ザ・デイリー・ショー","vote_average":6.36,"vote_count":577,"media_type":"tv"},{"adult":false,"backdrop_path":"/iEg2LHsFV3vC6LywkBAL3c1n9PP.jpg","genre_ids":[10767,35],"id":61818,"origin_country":["US"],"original_language":"en","original_name":"Late Night with Seth Meyers","overview":"","popularity":498.6756,"poster_path":"/rw0QaegwgKbRoB2CZe2lfewltT9.jpg","first_air_date":"2014-02-25","name":"レイト・ナイト・ウィズ・セス・マイヤーズ","vote_average":5.333,"vote_count":108,"media_type":"tv"},{"adult":false,"backdrop_path":"/hHMWfDlqKisD5zVcZfz3KEw5U3v.jpg","genre_ids":[18,10751],"id":50821,"origin_country":["HU"],"original_language":"hu","original_name":"Barátok közt","overview":"","popularity":558.4959,"poster_path":"/kBBbSgNchtMvsgD6z1oI1RRluHP.jpg","first_air_date":"1998-10-26","name":"Barátok közt","vote_average":3.2,"vote_count":14,"media_type":"tv"},{"adult":false,"backdrop_path":"/hvFCS0dMeC3ffiF4uYTKzUAkvYL.jpg","genre_ids":[35],"id":65701,"origin_country":["US"],"original_language":"en","original_name":"Good Mythical Morning","overview":"","popularity":553.8195,"poster_path":"/jMpBQr2aNOFAI6wsC47zsOG6qOh.jpg","first_air_date":"2012-01-09","name":"Good Mythical Morning","vote_average":7.038,"vote_count":80,"media_type":"tv"},{"adult":false,"backdrop_path":"/lksigd4PnpvvIY9oPHW2DEnHh5H.jpg","genre_ids":[],"id":70558,"origin_country":["US"],"original_language":"en","original_name":"NPR Tiny Desk Concerts","overview":"","popularity":617.9899,"poster_path":"/sJ6HdzajIVkC5G2kRROhNu8at43.jpg","first_air_date":"2008-04-22","name":"NPR Tiny Desk Concerts","vote_average":7.8,"vote_count":8,"media_type":"tv"},{"adult":false,"backdrop_path":"/mSkisNewxu55Ivar5EubhcIuoqn.jpg","genre_ids":[10764],"id":30957,"origin_country":["US","GB"],"original_language":"en","original_name":"The Amazing Race","overview":"","popularity":533.1862,"poster_path":"/x1jq0atcQg6UkaZpco0kFL6QHuM.jpg","first_air_date":"2001-09-05","name":"The Amazing Race","vote_average":6.873,"vote_count":153,"media_type":"tv"},{"adult":false,"backdrop_path":"/fgvM6m7gAd8kDAaLF16aflbOSAK.jpg","genre_ids":[18],"id":1416,"origin_country":["US"],"original_language":"en","original_name":"Grey's Anatomy","overview":"シアトル・グレース病院でインターンとしてのキャリアをスタートさせたメレディス・グレイ。彼女と、その仲間でもあり強力なライバルでもある同僚のインターンたちは、初日から厳しい現実を目の当たりにしながらも、それぞれに医師を目指して奮闘する。予想以上に厳しい生命の現場で、仕事に、恋に、悪戦苦闘しながら成長してゆくインターンたちの姿を描いた感動の医療ヒューマンドラマ。","popularity":689.7756,"poster_path":"/vcq57JdwwX4iSdOIaenPTM3uPvc.jpg","first_air_date":"2005-03-27","name":"グレイズ・アナトミー","vote_average":8.225,"vote_count":10538,"media_type":"tv"},{"adult":false,"backdrop_path":"/2o0cVL6fOa06aXd5xogZhD1h4ce.jpg","genre_ids":[10766,18],"id":14686,"origin_country":["DE"],"original_language":"de","original_name":"Alles was zählt","overview":"","popularity":340.5759,"poster_path":"/2qup6w78HhDiSii7v8vYgfEsz6E.jpg","first_air_date":"2006-09-04","name":"Alles was zählt","vote_average":5,"vote_count":7,"media_type":"tv"},{"adult":false,"backdrop_path":"/w88B4ooZ2LSYPw5107JOkjvI8PI.jpg","genre_ids":[80,18,9648],"id":4057,"origin_country":["US"],"original_language":"en","original_name":"Criminal Minds","overview":"FBI（米国連邦捜査局）に実在するエリート・プロファイラー集団、中でも先鋭な”行動分析課”、通称BAU（the Behavioral Analysis Unit）の活躍を描く。","popularity":495.8232,"poster_path":"/wLMQebhTApmn4F6Fzg6FovdwVvL.jpg","first_air_date":"2005-09-22","name":"クリミナル・マインド","vote_average":8.306,"vote_count":3852,"media_type":"tv"},{"adult":false,"backdrop_path":"/q8fmM50In8xGVW0iYoENPa71kAA.jpg","genre_ids":[10764],"id":1636,"origin_country":["GB"],"original_language":"en","original_name":"Top of the Pops","overview":"","popularity":322.2704,"poster_path":"/jjfTTjVYWyD6rGHVbnC44IrsJ7P.jpg","first_air_date":"1964-01-01","name":"Top of the Pops","vote_average":6.6,"vote_count":42,"media_type":"tv"},{"adult":false,"backdrop_path":"/3EGjqKhVHGsvNHvBIbxmqS17Aal.jpg","genre_ids":[10767,10763],"id":224,"origin_country":["GB"],"original_language":"en","original_name":"Match of the Day","overview":"","popularity":530.0288,"poster_path":"/paRFRd11WlFOxVbGnzjjCBym7FW.jpg","first_air_date":"1964-08-22","name":"Match of the Day","vote_average":7.511,"vote_count":47,"media_type":"tv"},{"adult":false,"backdrop_path":"/6jGVOu5NvnmSKh28ByWAJrTOEH2.jpg","genre_ids":[35,10767],"id":59941,"origin_country":["US"],"original_language":"en","original_name":"The Tonight Show Starring Jimmy Fallon","overview":"","popularity":474.6072,"poster_path":"/g4amxJvtpnY79J77xeamnAEUO8r.jpg","first_air_date":"2014-02-17","name":"ザ・トゥナイト・ショー・スターリング・ジミー・ファロン","vote_average":5.865,"vote_count":341,"media_type":"tv"},{"adult":false,"backdrop_path":"/hM2N4atUJguq1W0WiDRaMq7wcRF.jpg","genre_ids":[10767],"id":82873,"origin_country":["US"],"original_language":"en","original_name":"The Kelly Clarkson Show","overview":"","popularity":465.7981,"poster_path":"/sBix25bie9UQFzbarN51DpFO5ky.jpg","first_air_date":"2019-09-09","name":"ケリー・クラークソン・ショー","vote_average":6.4,"vote_count":64,"media_type":"tv"},{"adult":false,"backdrop_path":"/kkfqNkGQR5og5sDjJTxTVmI9PW.jpg","genre_ids":[80,18,10766],"id":72879,"origin_country":["FR"],"original_language":"fr","original_name":"Demain nous appartient","overview":"","popularity":411.8531,"poster_path":"/zMWldNZF0wS3L5XkDVFHxYhclcL.jpg","first_air_date":"2017-07-17","name":"Demain nous appartient","vote_average":6.343,"vote_count":67,"media_type":"tv"},{"adult":false,"backdrop_path":"/bWCAkYs4Sd8MOYHkzwbhrw2lgWh.jpg","genre_ids":[10763,10767],"id":4496,"origin_country":["US"],"original_language":"en","original_name":"Meet the Press","overview":"","popularity":351.7457,"poster_path":"/lisjDmT2xTykSZxCNvd7E3gQ9AI.jpg","first_air_date":"1947-11-06","name":"Meet the Press","vote_average":4,"vote_count":18,"media_type":"tv"},{"adult":false,"backdrop_path":"/cs4wxElH1XPgRLFq1FOtIFpeKqz.jpg","genre_ids":[35,10767],"id":4419,"origin_country":["US"],"original_language":"en","original_name":"Real Time with Bill Maher","overview":"","popularity":270.6127,"poster_path":"/pbpoLLp4kvnYVfnEGiEhagpJuVZ.jpg","first_air_date":"2003-02-21","name":"Real Time with Bill Maher","vote_average":6.002,"vote_count":221,"media_type":"tv"},{"adult":false,"backdrop_path":"/nFnzqHuiKF7mLjGb9GFKZ7SeuoB.jpg","genre_ids":[10763,10767],"id":3508,"origin_country":["US"],"original_language":"en","original_name":"Anderson Cooper 360°","overview":"","popularity":305.255,"poster_path":"/fi7KWbkJq3MirP32nsYOPQIc3oJ.jpg","first_air_date":"2003-09-08","name":"Anderson Cooper 360°","vote_average":5.1,"vote_count":8,"media_type":"tv"}],"total_pages":9991,"total_results":199818}