{"page":1,"results":[{"adult":false,"backdrop_path":"/56v2KjBlU4XaOv9rVYEQypROD7P.jpg","id":66732,"name":"ストレンジャー・シングス 未知の世界","original_name":"Stranger Things","overview":"姿を消した少年、人目を忍び行われる数々の実験、破壊的な超常現象、突然現れた少女。すべての不可解な謎をつなぐのは、小さな町に隠された恐ろしい秘密。","poster_path":"/DGWUKWfKr03DoEDKZSR1DhNqA.jpg","media_type":"tv","original_language":"en","genre_ids":[10765,9648,10759],"popularity":1453.1873,"first_air_date":"2016-07-15","vote_average":8.6,"vote_count":19293,"origin_country":["US"]},{"adult":false,"backdrop_path":"/5h2EsPKNDdB3MAtOk9MB9Ycg9Rz.jpg","id":1084242,"title":"ズートピア2","original_title":"Zootopia 2","overview":"警察学校を無事卒業し警察官となったニックと、ウサギ初の警官として以前にもまして熱心に任務に挑むジュディが再びバディを組むことに！ある日、ズートピアに突如現れたヘビ・ゲイリーをきっかけに、ジュディとニックはズートピアの過去の歴史にまつわる巨大な謎に挑むことになる。そこでジュディとニックふたりの絆もこれまで以上に試されることになるのだが…。","poster_path":"/twxXtxn3bLoLQONWCRlCTrgDLpG.jpg","media_type":"movie","original_language":"en","genre_ids":[16,10751,35,12,9648],"popularity":531.3208,"release_date":"2025-11-26","video":false,"vote_average":7.678,"vote_count":169},{"adult":false,"backdrop_path":"/ulEVubPGxPXik31qcmBTt4oupgM.jpg","id":701387,"title":"Bugonia","original_title":"Bugonia","overview":"","poster_path":"/oxgsAQDAAxA92mFGYCZllgWkH9J.jpg","media_type":"movie","original_language":"en","genre_ids":[80,878],"popularity":129.8461,"release_date":"2025-10-23","video":false,"vote_average":7.6,"vote_count":507},{"adult":false,"backdrop_path":"/8Y6A0bjCi1ZVAYQzf0LlEmckv5O.jpg","id":225171,"name":"プルリブス","original_name":"Pluribus","overview":"地球上で最も惨めな人物が、幸福から世界を救わなくてはならない。","poster_path":"/8v0kyakwaRCmqfuoLDfVSBe048N.jpg","media_type":"tv","original_language":"en","genre_ids":[18,10765],"popularity":90.2725,"first_air_date":"2025-11-06","vote_average":7.967,"vote_count":166,"origin_country":["US"]},{"adult":false,"backdrop_path":"/l8pwO23MCvqYumzozpxynCNfck1.jpg","id":967941,"title":"ウィキッド 永遠の約束","original_title":"Wicked: For Good","overview":"","poster_path":"/qzKgabRKPsMtFYqbjTLc37mwbBj.jpg","media_type":"movie","original_language":"en","genre_ids":[14,12,10749],"popularity":221.9589,"release_date":"2025-11-19","video":false,"vote_average":6.8,"vote_count":330},{"adult":false,"backdrop_path":"/7nAVXGHHtaNcdsqvDXmY6R9N0fG.jpg","id":1363123,"title":"ファミリー・プラン 2","original_title":"The Family Plan 2","overview":"暗殺者としての過去を葬った今、子供たちと充実したクリスマスを過ごすことだけがダンの望みだった。ところが娘が別の予定を立てていると知った彼は、ロンドンへの家族旅行を計画する。そのおかげで家族全員が予期せぬ敵に狙われることになる。","poster_path":"/4KaIKreLhebPuWhuz2WqRrPphw.jpg","media_type":"movie","original_language":"en","genre_ids":[28,35],"popularity":263.2653,"release_date":"2025-11-11","video":false,"vote_average":6.7,"vote_count":240},{"adult":false,"backdrop_path":"/zpEWFNqoN8Qg1SzMMHmaGyOBTdW.jpg","id":1054867,"title":"ワン・バトル・アフター・アナザー","original_title":"One Battle After Another","overview":"元革命家の頼りない中年男ボブ。彼はさらわれた愛娘を取り戻すため、かつての仲間や謎めいた空手のセンセイの助けを借りながら、恐ろしい軍人ロックジョーに立ち向かっていく。","poster_path":"/NiITrNf81jK998SYtHr81V4dD7.jpg","media_type":"movie","original_language":"en","genre_ids":[28,53,80],"popularity":138.3109,"release_date":"2025-09-23","video":false,"vote_average":7.492,"vote_count":1700},{"adult":false,"backdrop_path":"/iYxzsEBJnFzcgX0amOD6NcaCuPz.jpg","id":1242898,"title":"プレデター：バッドランド","original_title":"Predator: Badlands","overview":"","poster_path":"/w0J9P0T2a51l71xzIFwX3E8gCUF.jpg","media_type":"movie","original_language":"en","genre_ids":[28,878,12],"popularity":182.1091,"release_date":"2025-11-05","video":false,"vote_average":7.413,"vote_count":494},{"adult":false,"backdrop_path":"/u5NWHVhZ6HWc1fXnqn82cMar5St.jpg","id":1241983,"title":"トレイン・ドリームズ","original_title":"Train Dreams","overview":"20世紀初頭のアメリカで、森の伐採に従事する1人の労働者。激動の時代を多くを語らず謙虚に生き抜く男の愛と喪失の物語。","poster_path":"/l3zS4YnpOi4usyEXGJMtxSqDDyb.jpg","media_type":"movie","original_language":"en","genre_ids":[18],"popularity":67.8597,"release_date":"2025-11-05","video":false,"vote_average":7.327,"vote_count":168},{"adult":false,"backdrop_path":"/y6PLMIoHOP365rNDflD9VgnoALU.jpg","id":1218762,"title":"クリスマスイブには強盗を","original_title":"Jingle Bell Heist","overview":"運に見放されたしがない店員2人が企てたのは、ロンドンの高級百貨店からの金品強奪計画。クリスマスイブの決行に向けて準備を進めていくうちに、お互いのハートも盗んでしまうかも...!?","poster_path":"/rVOQF2Ucekug1B80A9crVx7Jn90.jpg","media_type":"movie","original_language":"en","genre_ids":[10749,80,35],"popularity":62.3549,"release_date":"2025-11-25","video":false,"vote_average":5.93,"vote_count":43},{"adult":false,"backdrop_path":"/2fOKVDoc2O3eZmBZesWPuE5kgPN.jpg","id":200875,"name":"IT／イット ウェルカム・トゥ・デリー \"それ\"が見えたら、終わり。","original_name":"IT: Welcome to Derry","overview":"映画館に忍び込み「ザ・ミュージックマン」を見ていた少年マティは追い出され、ある家族の車をヒッチハイクし乗せてもらったが徐々に家族の異常さに気付き行方不明になる。その失踪に疑問を持ったリリーたちがその映画館に赴くが悍ましい光景を目にする。","poster_path":"/nyy3BITeIjviv6PFIXtqvc8i6xi.jpg","media_type":"tv","original_language":"en","genre_ids":[18,9648],"popularity":268.9393,"first_air_date":"2025-10-26","vote_average":8.058,"vote_count":526,"origin_country":["US"]},{"adult":false,"backdrop_path":"/ufqytAlziHq5pljKByGJ8IKhtEZ.jpg","id":425274,"title":"Now You See Me: Now You Don't","original_title":"Now You See Me: Now You Don't","overview":"","poster_path":"/oD3Eey4e4Z259XLm3eD3WGcoJAh.jpg","media_type":"movie","original_language":"en","genre_ids":[53,80,9648],"popularity":118.5741,"release_date":"2025-11-12","video":false,"vote_average":6.325,"vote_count":285},{"adult":false,"backdrop_path":"/hpXBJxLD2SEf8l2CspmSeiHrBKX.jpg","id":1062722,"title":"フランケンシュタイン","original_title":"Frankenstein","overview":"ひとりの天才科学者と、その野心が創り出した恐ろしい怪物をめぐるメアリー・シェリーの古典小説の名作を、アカデミー賞受賞のギレルモ・デル・トロ監督が新たな視点で映像化。","poster_path":"/siIvWg36CiikM2f43GtiYxHXEDj.jpg","media_type":"movie","original_language":"en","genre_ids":[18,27,14],"popularity":192.548,"release_date":"2025-10-17","video":false,"vote_average":7.777,"vote_count":1965},{"adult":false,"backdrop_path":"/4BtL2vvEufDXDP4u6xQjjQ1Y2aT.jpg","id":1419406,"title":"捕风追影","original_title":"捕风追影","overview":"","poster_path":"/o25Tk1FYQi2BLk0OEAvx2h69QvB.jpg","media_type":"movie","original_language":"zh","genre_ids":[28,80,53],"popularity":370.3255,"release_date":"2025-08-16","video":false,"vote_average":6.374,"vote_count":127},{"adult":false,"backdrop_path":"/uJOkLO8zIjmkKKV0Cw0R4xiUmk9.jpg","id":1299655,"title":"Blue Moon","original_title":"Blue Moon","overview":"","poster_path":"/AetJmEIrhww0xnfktYgNl6ztDrl.jpg","media_type":"movie","original_language":"en","genre_ids":[18],"popularity":49.493,"release_date":"2025-10-17","video":false,"vote_average":6.855,"vote_count":38},{"adult":false,"backdrop_path":"/oVfucXvhutTpYExG9k06NJqnpT9.jpg","id":37854,"name":"ワンピース","original_name":"ワンピース","overview":"海賊王を夢見る少年モンキー・D・ルフィを主人公とする、「ひとつなぎの大秘宝（ワンピース）」を巡る海洋冒険ロマン。","poster_path":"/oag7edI9flSMawmNySEiSEJAbrf.jpg","media_type":"tv","original_language":"ja","genre_ids":[10759,35,16],"popularity":28.3732,"first_air_date":"1999-10-20","vote_average":8.722,"vote_count":5049,"origin_country":["JP"]},{"adult":false,"backdrop_path":"/m3WlBJJRbFPaut1QS0PbOG8Wezy.jpg","id":1327862,"title":"Regretting You","original_title":"Regretting You","overview":"","poster_path":"/z4gVnxTaks3anTycwKjDmvQSuWt.jpg","media_type":"movie","original_language":"en","genre_ids":[10749,18],"popularity":102.9613,"release_date":"2025-10-22","video":false,"vote_average":7.1,"vote_count":110},{"adult":false,"backdrop_path":"/2OHa6ukEq3Hce7Pc2kvu8wkmMFY.jpg","id":7451,"title":"トリプルX","original_title":"xXx","overview":"ザンダーは命を懸けたスポーツ“Xゲーム”で若者たちにその名を知られるカリスマ的な存在。どんな危険なゲームも平然とやってのけるその驚異的な身体能力と冷静な判断力が、やがて国家安全保障局（NSA）の目に留まる。NSAのベテラン・エージェント、ギボンズは強引にザンダーを説き伏せ、彼をシークレット・エージェントに任命する。任務とは、既に3人のエージェントが見破られ抹殺されていた過激な犯罪集団“アナーキー99”への潜入捜査だった。","poster_path":"/kqojzk0jxoP93RKKUXvQZ7wRhMG.jpg","media_type":"movie","original_language":"en","genre_ids":[28,12,53,80,18],"popularity":52.7937,"release_date":"2002-08-09","video":false,"vote_average":5.976,"vote_count":4675},{"adult":false,"backdrop_path":"/nt0HRxlzOXRpPJtl2FmeBCO6MeR.jpg","id":1246049,"title":"Dracula","original_title":"Dracula","overview":"","poster_path":"/vevuZVvb72VrbDzHiz4D8Z8XuGF.jpg","media_type":"movie","original_language":"fr","genre_ids":[27,14,10749],"popularity":193.2672,"release_date":"2025-07-30","video":false,"vote_average":7.052,"vote_count":472},{"adult":false,"backdrop_path":"/q71au2YjcwXBMZKNzNgjK7RZ3Hs.jpg","id":157741,"name":"ランドマン","original_name":"Landman","overview":"","poster_path":"/smwUCNk1wTn6nukCvQg5oA198Eq.jpg","media_type":"tv","original_language":"en","genre_ids":[18],"popularity":48.0702,"first_air_date":"2024-11-17","vote_average":8,"vote_count":303,"origin_country":["US"]}],"total_pages":500,"total_results":10000}