{"page":1,"results":[{"adult":false,"backdrop_path":"/eU7IfdWq8KQy0oNd4kKXS0QUR08.jpg","id":1061474,"title":"スーパーマン","original_title":"Superman","overview":"大手メディア「デイリー・プラネット」で平凡に働くクラーク・ケント、彼の本当の正体は人々を守るヒーロー「スーパーマン」。子どもも大人も、愛する地球で生きるすべての人を守り救うため、日々戦うスーパーマンは、誰からも愛される存在。そんな中、彼を地球の脅威とみなし暗躍する、最高の頭脳を持つ宿敵＝天才科学者して大富豪、レックス・ルーサーの世界を巻き込む綿密な計画が動き出すー","poster_path":"/47lpzGRQA6ALEmFZ2rRZOqoK1uP.jpg","media_type":"movie","original_language":"en","genre_ids":[878,12,28],"popularity":168.8676,"release_date":"2025-07-09","video":false,"vote_average":7.675,"vote_count":1692},{"adult":false,"backdrop_path":"/25g7mthXoJFcNZhAKz0evk17Bsx.jpg","id":157239,"name":"エイリアン：アース","original_name":"Alien: Earth","overview":"","poster_path":"/yueXS3q8BtoWekcHOATFHicLl3e.jpg","media_type":"tv","original_language":"en","genre_ids":[10765,18],"popularity":395.6075,"first_air_date":"2025-08-12","vote_average":8.1,"vote_count":104,"origin_country":["US"]},{"adult":false,"backdrop_path":"/fncHijpWjitFBmj7SX5z148XEhP.jpg","id":1234821,"title":"ジュラシック・ワールド／復活の大地","original_title":"Jurassic World Rebirth","overview":"","poster_path":"/pxKqRguqWooUJ2HTBJztZeZyTEk.jpg","media_type":"movie","original_language":"en","genre_ids":[878,12,28],"popularity":820.2156,"release_date":"2025-07-01","video":false,"vote_average":6.39,"vote_count":1510},{"adult":false,"backdrop_path":"/FRoX6ho4r388HONscYFPDwG4Ra.jpg","id":1254624,"title":"それでも夜は訪れる","original_title":"Night Always Comes","overview":"生活費が高騰した都市で、家族と共に暮らす家から強制退去を迫られる女性。一晩で2万5000ドルをかき集めなければならなくなり、絶望的な状況のなか、危険に飛び込んでいく。","poster_path":"/iK2dA5VWpT9xA9SBrv02k8TnNVu.jpg","media_type":"movie","original_language":"en","genre_ids":[53,18,80],"popularity":2.5468,"release_date":"2025-08-15","video":false,"vote_average":3.9,"vote_count":4},{"adult":false,"backdrop_path":"/Q2OajDi2kcO6yErb1IAyVDTKMs.jpg","id":1078605,"title":"Weapons","original_title":"Weapons","overview":"","poster_path":"/cpf7vsRZ0MYRQcnLWteD5jK9ymT.jpg","media_type":"movie","original_language":"en","genre_ids":[27,9648],"popularity":241.5381,"release_date":"2025-08-04","video":false,"vote_average":7.7,"vote_count":328},{"adult":false,"backdrop_path":"/ndUVIUfmtJ3vqGGTNQ0me6xbOMG.jpg","id":119051,"name":"ウェンズデー","original_name":"Wednesday","overview":"頭脳明晰(めいせき)で皮肉屋、そしていつも暗い面持ちのウェンズデー・アダムス。ネヴァーモア学園に入学した彼女が、新たな友や敵を作りながら、猟奇殺人の謎を探る。","poster_path":"/jXQ9smYSYKBpjnKj1qdnr223QLR.jpg","media_type":"tv","original_language":"en","genre_ids":[10765,9648,35],"popularity":733.0882,"first_air_date":"2022-11-23","vote_average":8.406,"vote_count":9404,"origin_country":["US"]},{"adult":false,"backdrop_path":"/uvSEjgc4vKWefFC6nWBCTQ22UwF.jpg","id":227114,"name":"バタフライ ～追う者と追われる者～","original_name":"Butterfly","overview":"韓国に潜伏している謎の元米諜報機関員デイビッド･チョンは、過去に下した不可能と思われた決断の代償が襲いかかり、人生が崩壊する。彼は、危険な若き暗殺者レベッカと、彼女が所属する民間諜報機関のキャディスに追われる身となる。","poster_path":"/x3AsJ1rK9CCaRPUR5UOVRUtFD1E.jpg","media_type":"tv","original_language":"en","genre_ids":[10759,18],"popularity":130.6798,"first_air_date":"2025-08-13","vote_average":7.318,"vote_count":22,"origin_country":["US"]},{"adult":false,"backdrop_path":"/9whEVuKte4Qi0LI4TzPf7glinJW.jpg","id":936108,"title":"劇場版スマーフ／おどるキノコ村の時空大冒険（パラレルアドベンチャー）","original_title":"Smurfs","overview":"","poster_path":"/7kQAZT58xudXuyeACTS5VAyoE6A.jpg","media_type":"movie","original_language":"en","genre_ids":[16,10751,14],"popularity":124.5419,"release_date":"2025-07-05","video":false,"vote_average":5.801,"vote_count":73},{"adult":false,"backdrop_path":"/7HqLLVjdjhXS0Qoz1SgZofhkIpE.jpg","id":1087192,"title":"ヒックとドラゴン","original_title":"How to Train Your Dragon","overview":"","poster_path":"/7nMp8ARe5vKcaFGbYjPTI14hgCe.jpg","media_type":"movie","original_language":"en","genre_ids":[14,10751,28,12],"popularity":300.9231,"release_date":"2025-06-06","video":false,"vote_average":8.027,"vote_count":1602},{"adult":false,"backdrop_path":"/l5jzuehwynnoEWUb9z25auHXQM.jpg","id":259909,"name":"Dexter: Resurrection","original_name":"Dexter: Resurrection","overview":"","poster_path":"/hIawSocuwqgNeRf3JuKuxgMHmSC.jpg","media_type":"tv","original_language":"en","genre_ids":[80,18],"popularity":63.2551,"first_air_date":"2025-07-13","vote_average":8.979,"vote_count":121,"origin_country":["US"]},{"adult":false,"backdrop_path":"/6fRwRD7GdCfg6owzmCT3VgQtowl.jpg","id":37854,"name":"ワンピース","original_name":"ワンピース","overview":"海賊王を夢見る少年モンキー・D・ルフィを主人公とする、「ひとつなぎの大秘宝（ワンピース）」を巡る海洋冒険ロマン。","poster_path":"/oag7edI9flSMawmNySEiSEJAbrf.jpg","media_type":"tv","original_language":"ja","genre_ids":[10759,35,16],"popularity":24.1528,"first_air_date":"1999-10-20","vote_average":8.724,"vote_count":4958,"origin_country":["JP"]},{"adult":false,"backdrop_path":"/y7tjLYcq2ZGy2DNG0ODhGX9Tm60.jpg","id":1106289,"title":"ザ・ピックアップ ~恋の強盗大作戦~","original_title":"The Pickup","overview":"いつもの現金回収現場は、一風変わった装甲車運転手ラッセル（エディ・マーフィ）とトラヴィス（ピート・デヴィッドソン）が、抜け目のない黒幕ゾーイ（キキ・パーマー）率いる冷酷な犯罪者たちに待ち伏せされるという、波乱万丈の展開を迎える。周囲が混乱に陥る中、この二人は、危険をはらみ、ぶつかり合う性格のぶつかり合い、そして悪化の一途を辿る最悪の一日を乗り越えなければならない。","poster_path":"/xmWEtyUp8NNNNdmchyRudLQs7Bm.jpg","media_type":"movie","original_language":"en","genre_ids":[28,35,80],"popularity":329.8964,"release_date":"2025-07-27","video":false,"vote_average":6.529,"vote_count":227},{"adult":false,"backdrop_path":"/5PJkK2iVXRO1ydrtgwuJdevmnOe.jpg","id":648878,"title":"Eddington","original_title":"Eddington","overview":"","poster_path":"/3owF0w0pSqd3TALVWrEBuRA8N6E.jpg","media_type":"movie","original_language":"en","genre_ids":[37,35,80],"popularity":96.9542,"release_date":"2025-07-16","video":false,"vote_average":6.727,"vote_count":121},{"adult":false,"backdrop_path":"/zav0v7gLWMu6pVwgsIAwt11GJ4C.jpg","id":1100988,"title":"28年後...","original_title":"28 Years Later","overview":"","poster_path":"/mqhKL4IEMFOCpVBXP0Jgcch5iYp.jpg","media_type":"movie","original_language":"en","genre_ids":[27,53,878],"popularity":151.3745,"release_date":"2025-06-18","video":false,"vote_average":6.84,"vote_count":1114},{"adult":false,"backdrop_path":"/1RgPyOhN4DRs225BGTlHJqCudII.jpg","id":1311031,"title":"劇場版「鬼滅の刃」無限城編 第一章 猗窩座再来","original_title":"劇場版「鬼滅の刃」無限城編 第一章 猗窩座再来","overview":"鬼となった妹・禰󠄀豆子を人間に戻すため鬼狩りの組織《鬼殺隊》に入った竈門炭治郎。入隊後、仲間である我妻善逸、嘴平伊之助と共に様々な鬼と戦い、成長しながら友情や絆を深めていく。そして炭治郎は《鬼殺隊》最高位の剣士である《柱》と共に戦い、「無限列車」では炎柱・煉󠄁獄杏寿郎、「遊郭」では音柱・宇髄天元、「刀鍛冶の里」では、霞柱・時透無一郎、恋柱・甘露寺蜜璃と共に激闘を繰り広げていった。その後、来たる鬼との決戦に備えて、隊士たちと共に《柱》による合同強化訓練《柱稽古》に挑んでいる最中、《鬼殺隊》の本部である産屋敷邸に現れた鬼舞辻󠄀無惨。お館様の危機に駆けつけた《柱》たちと炭治郎であったが、無惨の手によって謎の空間へと落とされてしまう。炭治郎たちが落下した先、それは鬼の根城≪無限城≫―”鬼殺隊”と”鬼”の最終決戦の火蓋が切って落とされる。","poster_path":"/tlNFKrkb0LzhnwvyiMSOoCB5dbj.jpg","media_type":"movie","original_language":"ja","genre_ids":[16,28,14,53],"popularity":298.3988,"release_date":"2025-07-18","video":false,"vote_average":7.2,"vote_count":73},{"adult":false,"backdrop_path":"/wO15XEgeLbeijtf3MQAUqWCxSxc.jpg","id":1007734,"title":"Mr.ノーバディ2","original_title":"Nobody 2","overview":"","poster_path":"/iyxwxDZCpIm0vIORaHpmgJv2BGF.jpg","media_type":"movie","original_language":"en","genre_ids":[28,53,80,35],"popularity":41.0103,"release_date":"2025-08-13","video":false,"vote_average":7.725,"vote_count":20},{"adult":false,"backdrop_path":"/mwVrLbaue8AqjFtF6lY6aakTtfb.jpg","id":196890,"name":"チーフ・オブ・ウォー","original_name":"Chief of War","overview":"ハワイの４つの王国が戦によって分断される中、勇猛な戦士カイアナは人々を団結させるため壮大な使命に挑む。そんな中、脅威が彼らの海岸に迫る。","poster_path":"/rsqpdalnL4RDiW4cLdfjZg5a7ie.jpg","media_type":"tv","original_language":"en","genre_ids":[18],"popularity":117.9899,"first_air_date":"2025-07-31","vote_average":6.9,"vote_count":74,"origin_country":["US"]},{"adult":false,"backdrop_path":"/rthMuZfFv4fqEU4JVbgSW9wQ8rs.jpg","id":986056,"title":"サンダーボルツ*","original_title":"Thunderbolts*","overview":"軟禁、恫喝も厭わない――！？過去に様々な事情を抱えた彼らが、集められた目的とは…。超クセ者ヴィランチーム「サンダーボルツ*」。一筋縄ではいかない彼らが、世界中をまだ見ぬ興奮と熱狂の渦に巻き込む！","poster_path":"/aiNHyXJKw1DhQVHUIKZKmaoQTez.jpg","media_type":"movie","original_language":"en","genre_ids":[28,878,12],"popularity":89.9832,"release_date":"2025-04-30","video":false,"vote_average":7.396,"vote_count":2202},{"adult":false,"backdrop_path":"/c9xmB53umjnrCMS4pZz11clF3yJ.jpg","id":980477,"title":"哪吒之魔童闹海","original_title":"哪吒之魔童闹海","overview":"","poster_path":"/bTMf8M7rZ21fChGdtsZtJj4Dfqh.jpg","media_type":"movie","original_language":"zh","genre_ids":[16,14,12,28],"popularity":200.2997,"release_date":"2025-01-29","video":false,"vote_average":7.997,"vote_count":289},{"adult":false,"backdrop_path":"/7uzhHIEOJ3AliYICXLzTpQ4Rkrn.jpg","id":537921,"title":"チョッキン!","original_title":"Fixed","overview":"去勢されることを知った犬のブルは、手術までに残された24時間を全力で楽しもうと、仲間のオス犬たちと冒険に繰り出すが...!? ちょっとお下劣な大人向けコメディアニメ。","poster_path":"/udtlwWSJ45S0uQm29BvFvjPJGW0.jpg","media_type":"movie","original_language":"en","genre_ids":[16,35],"popularity":44.9313,"release_date":"2025-08-13","video":false,"vote_average":7.023,"vote_count":22}],"total_pages":500,"total_results":10000}